Metadata-Version: 2.1
Name: chromedriver-py-auto
Version: 0.2.4
Summary: A wrapper around chromedriver-py library. Detects the Chrome version and installs the most suitable chromedriver-py version.
Home-page: https://github.com/AlirezaRoshanzamir/chromedriver-py-auto
Author: Alireza Roshanzamir
Author-email: a.roshanzamir1996@gmail.com
License: MIT License
Platform: UNKNOWN
